treasury/client.py
treasury/daily_treasury_statements.py
treasury/monthly_treasury_statement.py
treasury/offest_program.py
treasury/other_data.py
treasury/outstanding_debt.py
treasury/public_debt.py
treasury/revenue_and_payments.py
treasury/session.py
treasury/treasury_reports_on_receivables.py
us_federal_treasury_python_api-0.1.0.dist-info/LICENSE
us_federal_treasury_python_api-0.1.0.dist-info/METADATA
us_federal_treasury_python_api-0.1.0.dist-info/WHEEL
us_federal_treasury_python_api-0.1.0.dist-info/top_level.txt
us_federal_treasury_python_api-0.1.0.dist-info/RECORD
