Metadata-Version: 2.1
Name: us-federal-treasury-python-api
Version: 0.1.0
Summary: A Python application which is used to pull data from the United States Federal Treasury API.
Home-page: https://github.com/areed1192/us-federal-treasury-python-api
Author: Alex Reed
Author-email: coding.sigma@gmail.com
License: UNKNOWN
Platform: UNKNOWN
Classifier: Development Status :: 3 - Alpha
Classifier: Intended Audience :: Developers
Classifier: Intended Audience :: Science/Research
Classifier: Intended Audience :: Financial and Insurance Industry
Classifier: License :: OSI Approved :: MIT License
Classifier: Natural Language :: English
Classifier: Operating System :: OS Independent
Classifier: Programming Language :: Python :: 3.7
Classifier: Programming Language :: Python :: 3.8
Classifier: Topic :: Database
Classifier: Topic :: Education
Classifier: Topic :: Office/Business
Requires-Python: >3.7
Requires-Dist: requests (>=2.24.0)
